kerbitat/__init__.py
kerbitat/kerbitat.py
kerbitat/data/kernel_to_id.pkl
kerbitat/data/predictor.pt
kerbitat-0.0.2.dist-info/LICENSE
kerbitat-0.0.2.dist-info/METADATA
kerbitat-0.0.2.dist-info/WHEEL
kerbitat-0.0.2.dist-info/top_level.txt
kerbitat-0.0.2.dist-info/RECORD
