Metadata-Version: 2.1
Name: kerbitat
Version: 0.0.2
Summary: A small tool to pridict running time of a DNN model on NVIDIA GPUs.
Author-email: Siyuan Zhang <zhangsy3@shanghaitech.edu.cn>
Project-URL: Homepage, https://github.com/murez/kerbitat
Project-URL: Bug Tracker, https://github.com/murez/kerbitat/issues
Classifier: Programming Language :: Python :: 3
Classifier: Operating System :: OS Independent
Requires-Python: >=3.7
License-File: LICENSE
